[{"source": "bp_1974.06.04_doc_I-1", "target": "itaipu"}, {"source": "bp_1977.09.13_doc_I-17", "target": "itaipu"}, {"source": "bp_1974.06.04_doc_I-16", "target": "itaipu"}, {"source": "bp_1977.09.13_doc_II-1", "target": "itaipu"}, {"source": "bp_1974.06.04_doc_II-22", "target": "rio"}, {"source": "bp_1977.03.10_doc_IX-30", "target": "itaipu"}, {"source": "bp_1974.06.04_doc_II-16", "target": "itaipu"}, {"source": "bp_1974.06.04_doc_I-3", "target": "itaipu"}, {"source": "bp_1974.06.04_doc_II-23", "target": "itaipu"}, {"source": "bp_1974.06.04_doc_III-2", "target": "itaipu"}, {"source": "bp_1974.06.04_doc_I-6", "target": "itaipu"}, {"source": "bp_1977.03.10_doc_XIV-7", "target": "itaipu"}, {"source": "bp_1974.06.04_doc_IV-36", "target": "itaipu"}, {"source": "bp_1974.06.04_doc_IV-27", "target": "itaipu"}, {"source": "bp_1977.09.13_doc_I-1", "target": "itaipu"}, {"source": "bp_1977.03.10_doc_V-3", "target": "itaipu"}, {"source": "bp_1977.09.13_doc_II-2", "target": "itaipu"}, {"source": "d_1974.03.26_doc_XXXI-44", "target": "itaipu"}, {"source": "bp_1977.09.13_doc_I-14", "target": "itaipu"}, {"source": "bp_1977.03.10_doc_III-18", "target": "itaipu"}, {"source": "bp_1974.06.04_doc_I-1", "target": "rio"}, {"source": "bp_1977.09.13_doc_I-17", "target": "rio"}, {"source": "bp_1974.06.04_doc_I-16", "target": "rio"}, {"source": "bp_1977.09.13_doc_II-1", "target": "rio"}, {"source": "bp_1974.06.04_doc_II-22", "target": "cota"}, {"source": "bp_1977.03.10_doc_IX-30", "target": "rio"}, {"source": "bp_1974.06.04_doc_II-16", "target": "rio"}, {"source": "bp_1974.06.04_doc_I-3", "target": "rio"}, {"source": "bp_1974.06.04_doc_II-23", "target": "rio"}, {"source": "bp_1974.06.04_doc_III-2", "target": "rio"}, {"source": "bp_1974.06.04_doc_I-6", "target": "rio"}, {"source": "bp_1977.03.10_doc_XIV-7", "target": "rio"}, {"source": "bp_1974.06.04_doc_IV-36", "target": "rio"}, {"source": "bp_1974.06.04_doc_IV-27", "target": "rio"}, {"source": "bp_1977.09.13_doc_I-1", "target": "rio"}, {"source": "bp_1977.03.10_doc_V-3", "target": "rio"}, {"source": "bp_1977.09.13_doc_II-2", "target": "rio"}, {"source": "d_1974.03.26_doc_XXXI-44", "target": "rio"}, {"source": "bp_1977.09.13_doc_I-14", "target": "rio"}, {"source": "bp_1977.03.10_doc_III-18", "target": "rio"}, {"source": "bp_1974.06.04_doc_I-1", "target": "corpus"}, {"source": "bp_1977.09.13_doc_I-17", "target": "corpus"}, {"source": "bp_1974.06.04_doc_I-16", "target": "corpus"}, {"source": "bp_1977.09.13_doc_II-1", "target": "corpus"}, {"source": "bp_1974.06.04_doc_II-22", "target": "construcao"}, {"source": "bp_1977.03.10_doc_IX-30", "target": "operacao"}, {"source": "bp_1974.06.04_doc_II-16", "target": "corpus"}, {"source": "bp_1974.06.04_doc_I-3", "target": "corpus"}, {"source": "bp_1974.06.04_doc_II-23", "target": "cota"}, {"source": "bp_1974.06.04_doc_III-2", "target": "energia"}, {"source": "bp_1974.06.04_doc_I-6", "target": "corpus"}, {"source": "bp_1977.03.10_doc_XIV-7", "target": "corpus"}, {"source": "bp_1974.06.04_doc_IV-36", "target": "cota"}, {"source": "bp_1974.06.04_doc_IV-27", "target": "operacao"}, {"source": "bp_1977.09.13_doc_I-1", "target": "cota"}, {"source": "bp_1977.03.10_doc_V-3", "target": "cota"}, {"source": "bp_1977.09.13_doc_II-2", "target": "corpus"}, {"source": "d_1974.03.26_doc_XXXI-44", "target": "cota"}, {"source": "bp_1977.09.13_doc_I-14", "target": "corpus"}, {"source": "bp_1977.03.10_doc_III-18", "target": "corpus"}, {"source": "bp_1974.06.04_doc_I-1", "target": "cota"}, {"source": "bp_1977.09.13_doc_I-17", "target": "cota"}, {"source": "bp_1974.06.04_doc_I-16", "target": "cota"}, {"source": "bp_1977.09.13_doc_II-1", "target": "cota"}, {"source": "bp_1974.06.04_doc_II-22", "target": "barragem"}, {"source": "bp_1977.03.10_doc_IX-30", "target": "nivel"}, {"source": "bp_1974.06.04_doc_II-16", "target": "cota"}, {"source": "bp_1974.06.04_doc_I-3", "target": "cota"}, {"source": "bp_1974.06.04_doc_II-23", "target": "operacao"}, {"source": "bp_1974.06.04_doc_III-2", "target": "construcao"}, {"source": "bp_1974.06.04_doc_I-6", "target": "cota"}, {"source": "bp_1977.03.10_doc_XIV-7", "target": "cota"}, {"source": "bp_1974.06.04_doc_IV-36", "target": "operacao"}, {"source": "bp_1974.06.04_doc_IV-27", "target": "nivel"}, {"source": "bp_1977.09.13_doc_I-1", "target": "operacao"}, {"source": "bp_1977.03.10_doc_V-3", "target": "operacao"}, {"source": "bp_1977.09.13_doc_II-2", "target": "cota"}, {"source": "d_1974.03.26_doc_XXXI-44", "target": "operacao"}, {"source": "bp_1977.09.13_doc_I-14", "target": "cota"}, {"source": "bp_1977.03.10_doc_III-18", "target": "cota"}, {"source": "bp_1974.06.04_doc_I-1", "target": "operacao"}, {"source": "bp_1977.09.13_doc_I-17", "target": "energia"}, {"source": "bp_1974.06.04_doc_I-16", "target": "operacao"}, {"source": "bp_1977.09.13_doc_II-1", "target": "operacao"}, {"source": "bp_1974.06.04_doc_II-22", "target": "nivel"}, {"source": "bp_1977.03.10_doc_IX-30", "target": "aproveitamento"}, {"source": "bp_1974.06.04_doc_II-16", "target": "operacao"}, {"source": "bp_1974.06.04_doc_I-3", "target": "energia"}, {"source": "bp_1974.06.04_doc_II-23", "target": "energia"}, {"source": "bp_1974.06.04_doc_III-2", "target": "parana"}, {"source": "bp_1974.06.04_doc_I-6", "target": "operacao"}, {"source": "bp_1977.03.10_doc_XIV-7", "target": "operacao"}, {"source": "bp_1974.06.04_doc_IV-36", "target": "energia"}, {"source": "bp_1974.06.04_doc_IV-27", "target": "aproveitamento"}, {"source": "bp_1977.09.13_doc_I-1", "target": "energia"}, {"source": "bp_1977.03.10_doc_V-3", "target": "energia"}, {"source": "bp_1977.09.13_doc_II-2", "target": "operacao"}, {"source": "d_1974.03.26_doc_XXXI-44", "target": "energia"}, {"source": "bp_1977.09.13_doc_I-14", "target": "construcao"}, {"source": "bp_1977.03.10_doc_III-18", "target": "operacao"}, {"source": "bp_1974.06.04_doc_I-1", "target": "energia"}, {"source": "bp_1977.09.13_doc_I-17", "target": "construcao"}, {"source": "bp_1974.06.04_doc_I-16", "target": "energia"}, {"source": "bp_1977.09.13_doc_II-1", "target": "energia"}, {"source": "bp_1974.06.04_doc_II-22", "target": "parana"}, {"source": "bp_1977.03.10_doc_IX-30", "target": "projeto"}, {"source": "bp_1974.06.04_doc_II-16", "target": "energia"}, {"source": "bp_1974.06.04_doc_I-3", "target": "construcao"}, {"source": "bp_1974.06.04_doc_II-23", "target": "construcao"}, {"source": "bp_1974.06.04_doc_III-2", "target": "jusante"}, {"source": "bp_1974.06.04_doc_I-6", "target": "energia"}, {"source": "bp_1977.03.10_doc_XIV-7", "target": "energia"}, {"source": "bp_1974.06.04_doc_IV-36", "target": "construcao"}, {"source": "bp_1974.06.04_doc_IV-27", "target": "projeto"}, {"source": "bp_1977.09.13_doc_I-1", "target": "construcao"}, {"source": "bp_1977.03.10_doc_V-3", "target": "construcao"}, {"source": "bp_1977.09.13_doc_II-2", "target": "energia"}, {"source": "d_1974.03.26_doc_XXXI-44", "target": "construcao"}, {"source": "bp_1977.09.13_doc_I-14", "target": "parana"}, {"source": "bp_1977.03.10_doc_III-18", "target": "construcao"}, {"source": "bp_1974.06.04_doc_I-1", "target": "construcao"}, {"source": "bp_1977.09.13_doc_I-17", "target": "parana"}, {"source": "bp_1974.06.04_doc_I-16", "target": "construcao"}, {"source": "bp_1977.09.13_doc_II-1", "target": "construcao"}, {"source": "bp_1974.06.04_doc_II-22", "target": "obras"}, {"source": "bp_1974.06.04_doc_II-16", "target": "construcao"}, {"source": "bp_1974.06.04_doc_I-3", "target": "parana"}, {"source": "bp_1974.06.04_doc_II-23", "target": "parana"}, {"source": "bp_1974.06.04_doc_III-2", "target": "barragem"}, {"source": "bp_1974.06.04_doc_I-6", "target": "construcao"}, {"source": "bp_1977.03.10_doc_XIV-7", "target": "navegacao"}, {"source": "bp_1974.06.04_doc_IV-36", "target": "parana"}, {"source": "bp_1977.09.13_doc_I-1", "target": "parana"}, {"source": "bp_1977.03.10_doc_V-3", "target": "parana"}, {"source": "bp_1977.09.13_doc_II-2", "target": "construcao"}, {"source": "d_1974.03.26_doc_XXXI-44", "target": "parana"}, {"source": "bp_1977.09.13_doc_I-14", "target": "navegacao"}, {"source": "bp_1977.03.10_doc_III-18", "target": "navegacao"}, {"source": "bp_1974.06.04_doc_I-1", "target": "parana"}, {"source": "bp_1977.09.13_doc_I-17", "target": "jusante"}, {"source": "bp_1974.06.04_doc_I-16", "target": "parana"}, {"source": "bp_1977.09.13_doc_II-1", "target": "parana"}, {"source": "bp_1974.06.04_doc_II-22", "target": "projeto"}, {"source": "bp_1974.06.04_doc_II-16", "target": "parana"}, {"source": "bp_1974.06.04_doc_I-3", "target": "barragem"}, {"source": "bp_1974.06.04_doc_II-23", "target": "navegacao"}, {"source": "bp_1974.06.04_doc_III-2", "target": "parana"}, {"source": "bp_1974.06.04_doc_I-6", "target": "parana"}, {"source": "bp_1977.03.10_doc_XIV-7", "target": "jusante"}, {"source": "bp_1974.06.04_doc_IV-36", "target": "navegacao"}, {"source": "bp_1977.09.13_doc_I-1", "target": "jusante"}, {"source": "bp_1977.03.10_doc_V-3", "target": "navegacao"}, {"source": "bp_1977.09.13_doc_II-2", "target": "jusante"}, {"source": "d_1974.03.26_doc_XXXI-44", "target": "navegacao"}, {"source": "bp_1977.09.13_doc_I-14", "target": "barragem"}, {"source": "bp_1977.03.10_doc_III-18", "target": "jusante"}, {"source": "bp_1974.06.04_doc_I-1", "target": "jusante"}, {"source": "bp_1977.09.13_doc_I-17", "target": "barragem"}, {"source": "bp_1974.06.04_doc_I-16", "target": "navegacao"}, {"source": "bp_1977.09.13_doc_II-1", "target": "navegacao"}, {"source": "bp_1974.06.04_doc_II-16", "target": "navegacao"}, {"source": "bp_1974.06.04_doc_I-3", "target": "iguacu"}, {"source": "bp_1974.06.04_doc_II-23", "target": "jusante"}, {"source": "bp_1974.06.04_doc_III-2", "target": "iguacu"}, {"source": "bp_1974.06.04_doc_I-6", "target": "navegacao"}, {"source": "bp_1977.03.10_doc_XIV-7", "target": "barragem"}, {"source": "bp_1974.06.04_doc_IV-36", "target": "jusante"}, {"source": "bp_1977.09.13_doc_I-1", "target": "barragem"}, {"source": "bp_1977.03.10_doc_V-3", "target": "jusante"}, {"source": "bp_1977.09.13_doc_II-2", "target": "barragem"}, {"source": "d_1974.03.26_doc_XXXI-44", "target": "jusante"}, {"source": "bp_1977.09.13_doc_I-14", "target": "nivel"}, {"source": "bp_1977.03.10_doc_III-18", "target": "barragem"}, {"source": "bp_1974.06.04_doc_I-1", "target": "barragem"}, {"source": "bp_1977.09.13_doc_I-17", "target": "nivel"}, {"source": "bp_1974.06.04_doc_I-16", "target": "barragem"}, {"source": "bp_1977.09.13_doc_II-1", "target": "barragem"}, {"source": "bp_1974.06.04_doc_II-16", "target": "jusante"}, {"source": "bp_1974.06.04_doc_I-3", "target": "trecho"}, {"source": "bp_1974.06.04_doc_II-23", "target": "barragem"}, {"source": "bp_1974.06.04_doc_III-2", "target": "obras"}, {"source": "bp_1974.06.04_doc_I-6", "target": "jusante"}, {"source": "bp_1977.03.10_doc_XIV-7", "target": "projeto"}, {"source": "bp_1974.06.04_doc_IV-36", "target": "barragem"}, {"source": "bp_1977.09.13_doc_I-1", "target": "nivel"}, {"source": "bp_1977.03.10_doc_V-3", "target": "barragem"}, {"source": "bp_1977.09.13_doc_II-2", "target": "nivel"}, {"source": "d_1974.03.26_doc_XXXI-44", "target": "barragem"}, {"source": "bp_1977.09.13_doc_I-14", "target": "iguacu"}, {"source": "bp_1977.03.10_doc_III-18", "target": "nivel"}, {"source": "bp_1974.06.04_doc_I-1", "target": "nivel"}, {"source": "bp_1977.09.13_doc_I-17", "target": "iguacu"}, {"source": "bp_1974.06.04_doc_I-16", "target": "nivel"}, {"source": "bp_1977.09.13_doc_II-1", "target": "nivel"}, {"source": "bp_1974.06.04_doc_II-16", "target": "barragem"}, {"source": "bp_1974.06.04_doc_I-3", "target": "projeto"}, {"source": "bp_1974.06.04_doc_II-23", "target": "nivel"}, {"source": "bp_1974.06.04_doc_III-2", "target": "aproveitamento"}, {"source": "bp_1974.06.04_doc_I-6", "target": "barragem"}, {"source": "bp_1974.06.04_doc_IV-36", "target": "nivel"}, {"source": "bp_1977.09.13_doc_I-1", "target": "parana"}, {"source": "bp_1977.03.10_doc_V-3", "target": "nivel"}, {"source": "bp_1977.09.13_doc_II-2", "target": "parana"}, {"source": "d_1974.03.26_doc_XXXI-44", "target": "nivel"}, {"source": "bp_1977.09.13_doc_I-14", "target": "aguas"}, {"source": "bp_1977.03.10_doc_III-18", "target": "parana"}, {"source": "bp_1974.06.04_doc_I-1", "target": "iguacu"}, {"source": "bp_1977.09.13_doc_I-17", "target": "trecho"}, {"source": "bp_1974.06.04_doc_I-16", "target": "parana"}, {"source": "bp_1977.09.13_doc_II-1", "target": "parana"}, {"source": "bp_1974.06.04_doc_II-16", "target": "nivel"}, {"source": "bp_1974.06.04_doc_II-23", "target": "parana"}, {"source": "bp_1974.06.04_doc_III-2", "target": "projeto"}, {"source": "bp_1974.06.04_doc_I-6", "target": "nivel"}, {"source": "bp_1974.06.04_doc_IV-36", "target": "parana"}, {"source": "bp_1977.09.13_doc_I-1", "target": "iguacu"}, {"source": "bp_1977.03.10_doc_V-3", "target": "parana"}, {"source": "bp_1977.09.13_doc_II-2", "target": "iguacu"}, {"source": "d_1974.03.26_doc_XXXI-44", "target": "parana"}, {"source": "bp_1977.09.13_doc_I-14", "target": "obras"}, {"source": "bp_1977.03.10_doc_III-18", "target": "iguacu"}, {"source": "bp_1974.06.04_doc_I-1", "target": "trecho"}, {"source": "bp_1977.09.13_doc_I-17", "target": "projeto"}, {"source": "bp_1974.06.04_doc_I-16", "target": "iguacu"}, {"source": "bp_1977.09.13_doc_II-1", "target": "iguacu"}, {"source": "bp_1974.06.04_doc_II-16", "target": "parana"}, {"source": "bp_1974.06.04_doc_II-23", "target": "iguacu"}, {"source": "bp_1974.06.04_doc_III-2", "target": "eletrobras"}, {"source": "bp_1974.06.04_doc_I-6", "target": "parana"}, {"source": "bp_1974.06.04_doc_IV-36", "target": "iguacu"}, {"source": "bp_1977.09.13_doc_I-1", "target": "aguas"}, {"source": "bp_1977.03.10_doc_V-3", "target": "iguacu"}, {"source": "bp_1977.09.13_doc_II-2", "target": "obras"}, {"source": "d_1974.03.26_doc_XXXI-44", "target": "iguacu"}, {"source": "bp_1977.09.13_doc_I-14", "target": "aproveitamento"}, {"source": "bp_1977.03.10_doc_III-18", "target": "obras"}, {"source": "bp_1974.06.04_doc_I-1", "target": "projeto"}, {"source": "bp_1977.09.13_doc_I-17", "target": "eletrobras"}, {"source": "bp_1974.06.04_doc_I-16", "target": "aproveitamento"}, {"source": "bp_1977.09.13_doc_II-1", "target": "aproveitamento"}, {"source": "bp_1974.06.04_doc_II-16", "target": "iguacu"}, {"source": "bp_1974.06.04_doc_II-23", "target": "obras"}, {"source": "bp_1974.06.04_doc_I-6", "target": "iguacu"}, {"source": "bp_1974.06.04_doc_IV-36", "target": "aguas"}, {"source": "bp_1977.09.13_doc_I-1", "target": "obras"}, {"source": "bp_1977.03.10_doc_V-3", "target": "aguas"}, {"source": "bp_1977.09.13_doc_II-2", "target": "aproveitamento"}, {"source": "d_1974.03.26_doc_XXXI-44", "target": "aguas"}, {"source": "bp_1977.09.13_doc_I-14", "target": "trecho"}, {"source": "bp_1977.03.10_doc_III-18", "target": "aproveitamento"}, {"source": "bp_1974.06.04_doc_I-1", "target": "eletrobras"}, {"source": "bp_1974.06.04_doc_I-16", "target": "projeto"}, {"source": "bp_1977.09.13_doc_II-1", "target": "projeto"}, {"source": "bp_1974.06.04_doc_II-16", "target": "obras"}, {"source": "bp_1974.06.04_doc_II-23", "target": "trecho"}, {"source": "bp_1974.06.04_doc_I-6", "target": "aguas"}, {"source": "bp_1974.06.04_doc_IV-36", "target": "obras"}, {"source": "bp_1977.09.13_doc_I-1", "target": "aproveitamento"}, {"source": "bp_1977.03.10_doc_V-3", "target": "obras"}, {"source": "bp_1977.09.13_doc_II-2", "target": "trecho"}, {"source": "d_1974.03.26_doc_XXXI-44", "target": "obras"}, {"source": "bp_1977.09.13_doc_I-14", "target": "projeto"}, {"source": "bp_1977.03.10_doc_III-18", "target": "trecho"}, {"source": "bp_1974.06.04_doc_I-16", "target": "eletrobras"}, {"source": "bp_1977.09.13_doc_II-1", "target": "eletrobras"}, {"source": "bp_1974.06.04_doc_II-16", "target": "aproveitamento"}, {"source": "bp_1974.06.04_doc_II-23", "target": "projeto"}, {"source": "bp_1974.06.04_doc_I-6", "target": "obras"}, {"source": "bp_1974.06.04_doc_IV-36", "target": "trecho"}, {"source": "bp_1977.09.13_doc_I-1", "target": "trecho"}, {"source": "bp_1977.03.10_doc_V-3", "target": "aproveitamento"}, {"source": "bp_1977.09.13_doc_II-2", "target": "projeto"}, {"source": "d_1974.03.26_doc_XXXI-44", "target": "aproveitamento"}, {"source": "bp_1974.06.04_doc_II-16", "target": "trecho"}, {"source": "bp_1974.06.04_doc_I-6", "target": "aproveitamento"}, {"source": "bp_1974.06.04_doc_IV-36", "target": "projeto"}, {"source": "bp_1977.09.13_doc_I-1", "target": "eletrobras"}, {"source": "bp_1977.03.10_doc_V-3", "target": "trecho"}, {"source": "bp_1977.09.13_doc_II-2", "target": "eletrobras"}, {"source": "d_1974.03.26_doc_XXXI-44", "target": "trecho"}, {"source": "bp_1974.06.04_doc_I-6", "target": "trecho"}, {"source": "bp_1974.06.04_doc_IV-36", "target": "eletrobras"}, {"source": "bp_1977.03.10_doc_V-3", "target": "projeto"}, {"source": "d_1974.03.26_doc_XXXI-44", "target": "projeto"}, {"source": "bp_1974.06.04_doc_I-6", "target": "projeto"}, {"source": "bp_1977.03.10_doc_V-3", "target": "eletrobras"}, {"source": "d_1974.03.26_doc_XXXI-44", "target": "eletrobras"}, {"source": "bp_1974.06.04_doc_I-6", "target": "eletrobras"}]