[{"name": "Antonio Azeredo Da Silveira", "count": 2.0, "docs": ["ag_1973.11.20_doc_I-66", "ag_1974.03.15_doc_II-32", "ag_1974.01.22_doc_IV-12", "ag_1973.11.20_doc_II-63", "ag_1973.11.20_doc_I-92"]}, {"name": "Dilermando Gomes Monteiro", "count": 1.0020470829068577, "docs": ["ag_1974.03.15_doc_II-32"]}, {"name": "Ernesto Geisel", "count": 1.4107813033094507, "docs": ["ag_1973.11.20_doc_VI-160"]}, {"name": "Gama Filho", "count": 1.0010235414534288, "docs": ["ag_1974.03.00-1_doc_III-4"]}, {"name": "Paulo Cabral", "count": 1.0221767314909587, "docs": ["ag_1974.01.22_doc_I-8"]}]