[{"name": "alfredo buzaid", "count": 3.4190225827029095, "docs": ["d_1974.03.26_doc_XV-4"]}, {"name": "alfredo stroessner", "count": 13.054896016631886, "docs": ["d_1974.03.26_doc_X-17"]}, {"name": "antonio azeredo da silveira", "count": 19.6887445579689, "docs": ["d_1974.03.26_doc_XXII-15", "ag_1974.01.22_doc_III-38", "d_1974.03.26_doc_XV-4", "ag_1974.03.00-2_doc_22", "d_1974.03.26_doc_X-25", "ag_1974.03.25_doc_V-42"]}, {"name": "eurico ", "count": 8.905619350311527, "docs": ["ag_1974.01.16_doc_II-3"]}, {"name": "fernando costa", "count": 1.7095112913514547, "docs": ["ag_1974.01.16_doc_II-3"]}, {"name": "francisco campos", "count": 1.7095112913514547, "docs": ["ag_1974.01.16_doc_II-3"]}, {"name": "golbery do couto e silva", "count": 11.86830693724869, "docs": ["ag_1974.01.22_doc_V-137", "d_1974.03.26_doc_X-25"]}, {"name": "gomes pereira", "count": 4.419022582702909, "docs": ["ag_1974.03.25_doc_V-42"]}, {"name": "gustavo capanema", "count": 4.419022582702909, "docs": ["ag_1974.01.16_doc_II-3", "d_1974.03.26_doc_XV-4"]}, {"name": "horacio lafer", "count": 1.7095112913514547, "docs": ["d_1974.03.26_doc_XV-4"]}, {"name": "in tam", "count": 3.4190225827029095, "docs": ["d_1974.03.26_doc_XV-4"]}, {"name": "marcial dias pequeno", "count": 0.0, "docs": ["d_1974.03.26_doc_XV-4"]}, {"name": "nilton de oliveira", "count": 0.0, "docs": ["d_1974.03.26_doc_X-17"]}, {"name": "oswaldo aranha", "count": 5.6788735872675735, "docs": ["ag_1974.01.16_doc_II-3"]}, {"name": "ramos de azevedo", "count": 3.4190225827029095, "docs": ["ag_1974.03.25_doc_V-42"]}, {"name": "raul fernandes", "count": 3.4190225827029095, "docs": ["d_1974.03.26_doc_XV-4"]}, {"name": "saraiva guerreiro", "count": 11.637250103494376, "docs": ["d_1974.03.26_doc_X-17"]}, {"name": "yoshiro ando", "count": 0.0, "docs": ["d_1974.03.26_doc_XV-4"]}]